hjkl_2048.py
hjkl_2048-1.1.0.dist-info/entry_points.txt
hjkl_2048-1.1.0.dist-info/WHEEL
hjkl_2048-1.1.0.dist-info/METADATA
hjkl_2048-1.1.0.dist-info/RECORD
