Metadata-Version: 2.1
Name: hjkl-2048
Version: 1.1.0
Summary: play 2048 with hjkl
Author: worldmaker
Author-email: worldmaker18349276@gmail.com
Requires-Python: >=3.8,<4.0
Classifier: Programming Language :: Python :: 3
Classifier: Programming Language :: Python :: 3.10
Classifier: Programming Language :: Python :: 3.8
Classifier: Programming Language :: Python :: 3.9
Requires-Dist: numpy (>=1.18.5,<2.0.0)
